pci_agent/__init__.py
pci_agent/__main__.py
pci_agent/agent.py
pci_agent/config.py
pci_agent/context.py
pci_agent/policy.py
pci_agent-0.1.0.dist-info/METADATA
pci_agent-0.1.0.dist-info/WHEEL
pci_agent-0.1.0.dist-info/licenses/LICENSE
pci_agent-0.1.0.dist-info/RECORD
