Metadata-Version: 2.4
Name: pci-agent
Version: 0.1.0
Summary: Layer 2: Local AI agent for Personal Context Infrastructure
Project-URL: Homepage, https://github.com/peteski22/pci-agent
Project-URL: Repository, https://github.com/peteski22/pci-agent
Project-URL: Issues, https://github.com/peteski22/pci-agent/issues
Author: PCI Contributors
License: Apache-2.0
License-File: LICENSE
Keywords: agent,ai,local-first,pci,privacy
Classifier: Development Status :: 3 - Alpha
Classifier: Intended Audience :: Developers
Classifier: License :: OSI Approved :: Apache Software License
Classifier: Programming Language :: Python :: 3
Classifier: Programming Language :: Python :: 3.12
Requires-Python: >=3.12
Requires-Dist: pydantic>=2.0.0
Provides-Extra: llm
Requires-Dist: llama-cpp-python>=0.3.0; extra == 'llm'
